chat_with_functions/__init__.py
chat_with_functions/cached_streaming.py
chat_with_functions/caches.py
chat_with_functions/chat.py
chat_with_functions/data_structures.py
chat_with_functions/function_calling_structure.py
chat_with_functions/openai_api.py
chat_with_functions/openai_util.py
chat_with_functions/streaming.py
chat_with_functions/util.py
chat_with_functions-0.1.2.dist-info/METADATA
chat_with_functions-0.1.2.dist-info/WHEEL
chat_with_functions-0.1.2.dist-info/RECORD
